qualtrutils/__init__.py
qualtrutils/qualtrics.py
qualtrutils-0.1.5.dist-info/LICENSE
qualtrutils-0.1.5.dist-info/METADATA
qualtrutils-0.1.5.dist-info/WHEEL
qualtrutils-0.1.5.dist-info/top_level.txt
qualtrutils-0.1.5.dist-info/RECORD
