Metadata-Version: 2.1
Name: qualtrutils
Version: 0.1.5
Summary: A simple package to interact with the Qualtrics API
Home-page: https://github.com/emanuele-albini/qualtrutils
Author: Emanuele Albini
License: UNKNOWN
Project-URL: Documentation, https://emanuele-albini.github.io/qualtrutils
Project-URL: Source Code, https://github.com/emanuele-albini/qualtrutils
Project-URL: Bug Tracker, https://github.com/emanuele-albini/qualtrutils/issues
Project-URL: Author Website, https://www.emanuelealbini.com
Keywords: Qualtrics,API,surveys,survey
Platform: any
Classifier: Programming Language :: Python :: 3
Classifier: Programming Language :: Python :: 3.6
Classifier: Programming Language :: Python :: 3.7
Classifier: Programming Language :: Python :: 3.8
Classifier: Programming Language :: Python :: 3.9
Classifier: Operating System :: OS Independent
Classifier: Development Status :: 5 - Production/Stable
Classifier: License :: OSI Approved :: MIT License
Requires-Python: >=3.6
License-File: LICENSE
Requires-Dist: tqdm
Requires-Dist: toml
Requires-Dist: requests
